jeml/__init__.py
jeml/decoder.py
jeml/encoder.py
jeml/engine/__init__.py
jeml/engine/jemlErrorHandler.py
jeml/engine/jemlLexer.py
jeml/engine/jemlListener.py
jeml/engine/jemlParser.py
jeml-1.0.1.dist-info/LICENSE
jeml-1.0.1.dist-info/METADATA
jeml-1.0.1.dist-info/WHEEL
jeml-1.0.1.dist-info/top_level.txt
jeml-1.0.1.dist-info/RECORD
